arabic_to_roman/__init__.py
arabic_to_roman/main.py
arabic_to_roman-1.0.0.dist-info/entry_points.txt
arabic_to_roman-1.0.0.dist-info/LICENSE
arabic_to_roman-1.0.0.dist-info/WHEEL
arabic_to_roman-1.0.0.dist-info/METADATA
arabic_to_roman-1.0.0.dist-info/RECORD
