Metadata-Version: 2.1
Name: arabic-to-roman
Version: 1.0.0
Summary: Arabic number to Roman numeral converter
License: MIT
Author: Carl Mattsson
Author-email: carl.mattsson@gmail.com
Requires-Python: >=3.8,<4.0
Classifier: License :: OSI Approved :: MIT License
Classifier: Programming Language :: Python :: 3
Classifier: Programming Language :: Python :: 3.10
Classifier: Programming Language :: Python :: 3.8
Classifier: Programming Language :: Python :: 3.9
